<?xml version="1.0" encoding="utf-8"?>
<annotation>
	<filename>0006600.jpg</filename>
	<folder>BLR-2018-03-22_17-39-26_2_frontFar_left_14</folder>
	<size>
		<width>1280</width>
		<height>964</height>
		<depth>3</depth>
	</size>
	<object>
		<name>person</name>
		<bndbox>
			<xmin>881</xmin>
			<ymax>516</ymax>
			<xmax>908</xmax>
			<ymin>469</ymin>
		</bndbox>
	</object>
	<object>
		<name>person</name>
		<bndbox>
			<xmin>914</xmin>
			<ymax>546</ymax>
			<xmax>939</xmax>
			<ymin>469</ymin>
		</bndbox>
	</object>
	<object>
		<name>person</name>
		<bndbox>
			<xmin>943</xmin>
			<ymax>544</ymax>
			<xmax>973</xmax>
			<ymin>464</ymin>
		</bndbox>
	</object>
	<object>
		<name>person</name>
		<bndbox>
			<xmin>1049</xmin>
			<ymax>544</ymax>
			<xmax>1076</xmax>
			<ymin>491</ymin>
		</bndbox>
	</object>
	<object>
		<name>motorcycle</name>
		<bndbox>
			<xmin>817</xmin>
			<ymax>556</ymax>
			<xmax>873</xmax>
			<ymin>492</ymin>
		</bndbox>
	</object>
	<object>
		<name>rider</name>
		<bndbox>
			<xmin>823</xmin>
			<ymax>548</ymax>
			<xmax>873</xmax>
			<ymin>471</ymin>
		</bndbox>
	</object>
	<object>
		<name>autorickshaw</name>
		<bndbox>
			<xmin>520</xmin>
			<ymax>683</ymax>
			<xmax>752</xmax>
			<ymin>369</ymin>
		</bndbox>
	</object>
	<object>
		<name>car</name>
		<bndbox>
			<xmin>683</xmin>
			<ymax>963</ymax>
			<xmax>1275</xmax>
			<ymin>538</ymin>
		</bndbox>
	</object>
</annotation>